pypathway/__init__.py
pypathway/utils.py
pypathway/core/.DS_Store
pypathway/core/BioPAXImpl.py
pypathway/core/GPMLImpl.py
pypathway/core/KGMLImpl.py
pypathway/core/SBGNImpl.py
pypathway/core/__init__.py
pypathway/core/general.py
pypathway/query/.DS_Store
pypathway/query/__init__.py
pypathway/query/common.py
pypathway/query/database.py
pypathway/query/network.py
pypathway/static/.DS_Store
pypathway/static/box.html
pypathway/static/GPML/.DS_Store
pypathway/static/GPML/gpml.html
pypathway/static/GPML/.idea/GPML.iml
pypathway/static/GPML/.idea/modules.xml
pypathway/static/GPML/.idea/workspace.xml
pypathway/static/GPML/css/.DS_Store
pypathway/static/GPML/css/font-awesome.min.css
pypathway/static/GPML/css/jquery-ui-1.10.3.custom.css
pypathway/static/GPML/css/jquery-ui.css
pypathway/static/GPML/css/jquery.qtip.css
pypathway/static/GPML/css/main.css
pypathway/static/GPML/css/bootstrap/.DS_Store
pypathway/static/GPML/css/bootstrap/bootstrap.min.css
pypathway/static/GPML/font/fontawesome-webfont.woff
pypathway/static/GPML/gpml_data/.DS_Store
pypathway/static/GPML/gpml_data/config.json
pypathway/static/GPML/gpml_data/custom.css
pypathway/static/GPML/gpml_data/interface_gpml.js
pypathway/static/GPML/gpml_data/interface_gpml_back.js
pypathway/static/GPML/gpml_data/pathway.xml
pypathway/static/GPML/js/.DS_Store
pypathway/static/GPML/js/bootstrap.min.js
pypathway/static/GPML/js/custom-element.js
pypathway/static/GPML/js/d3.min.js
pypathway/static/GPML/js/echarts.common.min.js
pypathway/static/GPML/js/jquery-2.0.3.min.js
pypathway/static/GPML/js/jquery-ui-1.10.3.custom.min.js
pypathway/static/GPML/js/jquery.qtip.js
pypathway/static/GPML/js/mithril.min.js
pypathway/static/GPML/js/polyfill.js
pypathway/static/GPML/js/polyfills.bundle.min.js
pypathway/static/GPML/js/pvjs.core.min.mod.js
pypathway/static/GPML/js/pvjs.core.mod.js
pypathway/static/GPML/js/pvjs.custom-element.js
pypathway/static/GPML/js/pvjs.custom-element.min.js
pypathway-0.2.4.2.dist-info/DESCRIPTION.rst
pypathway-0.2.4.2.dist-info/METADATA
pypathway-0.2.4.2.dist-info/RECORD
pypathway-0.2.4.2.dist-info/WHEEL
pypathway-0.2.4.2.dist-info/metadata.json
pypathway-0.2.4.2.dist-info/top_level.txt
