Metadata-Version: 2.0
Name: pypathway
Version: 0.2.4.2
Summary: A Python package for playing with pathways
Home-page: https://github.com/iseekwonderful/pypathway
Author: sheep
Author-email: sss3barry@gmail.com
License: GNU General Public License v3 (GPLv3)
Keywords: pypathway
Platform: UNKNOWN
Classifier: Development Status :: 2 - Pre-Alpha
Classifier: Intended Audience :: Developers
Classifier: License :: OSI Approved :: GNU General Public License v3 (GPLv3)
Classifier: Natural Language :: English
Classifier: Programming Language :: Python :: 2
Classifier: Programming Language :: Python :: 2.7
Classifier: Programming Language :: Python :: 3
Classifier: Programming Language :: Python :: 3.5
Requires-Dist: requests (>=1.0)
Requires-Dist: ipython
Requires-Dist: jupyter
Requires-Dist: echarts-python
Requires-Dist: numpy
